prelude_django_admin_toolkit/.gitignore
prelude_django_admin_toolkit/__init__.py
prelude_django_admin_toolkit/admin.py
prelude_django_admin_toolkit/apps.py
prelude_django_admin_toolkit/customizer.py
prelude_django_admin_toolkit/forms.py
prelude_django_admin_toolkit/locale/pt_BR/LC_MESSAGES/django.mo
prelude_django_admin_toolkit/locale/pt_BR/LC_MESSAGES/django.po
prelude_django_admin_toolkit/migrations/__init__.py
prelude_django_admin_toolkit/static/.gitignore
prelude_django_admin_toolkit/static/prelude_django_admin_toolkit/.gitignore
prelude_django_admin_toolkit/static/prelude_django_admin_toolkit/css/base_theme.css
prelude_django_admin_toolkit/static/prelude_django_admin_toolkit/css/normalize.css
prelude_django_admin_toolkit/static/prelude_django_admin_toolkit/css/site_default.css
prelude_django_admin_toolkit/static/prelude_django_admin_toolkit/css/site_yellow.css
prelude_django_admin_toolkit/static/prelude_django_admin_toolkit/icon/android-chrome-192x192.png
prelude_django_admin_toolkit/static/prelude_django_admin_toolkit/icon/android-chrome-512x512.png
prelude_django_admin_toolkit/static/prelude_django_admin_toolkit/icon/apple-touch-icon.png
prelude_django_admin_toolkit/static/prelude_django_admin_toolkit/icon/favicon-16x16.png
prelude_django_admin_toolkit/static/prelude_django_admin_toolkit/icon/favicon-32x32.png
prelude_django_admin_toolkit/static/prelude_django_admin_toolkit/icon/favicon.ico
prelude_django_admin_toolkit/static/prelude_django_admin_toolkit/icon/site.webmanifest
prelude_django_admin_toolkit/static/prelude_django_admin_toolkit/js/admin_changelist.js
prelude_django_admin_toolkit/static/prelude_django_admin_toolkit/js/vendor.js
prelude_django_admin_toolkit/templates/admin/404.html
prelude_django_admin_toolkit/templates/admin/500.html
prelude_django_admin_toolkit/templates/admin/actions.html
prelude_django_admin_toolkit/templates/admin/app_index.html
prelude_django_admin_toolkit/templates/admin/app_list.html
prelude_django_admin_toolkit-0.14.8.dist-info/WHEEL
prelude_django_admin_toolkit-0.14.8.dist-info/METADATA
prelude_django_admin_toolkit-0.14.8.dist-info/RECORD
