Metadata-Version: 2.1
Name: prelude-django-admin-toolkit
Version: 0.14.8
Summary: An alternative Django Admin theme with Batteries; project Bruh
Author: Jonhnatha Trigueiro
Author-email: joepreludian@gmail.com
Requires-Python: >=3.8,<4.0
Classifier: Programming Language :: Python :: 3
Classifier: Programming Language :: Python :: 3.8
Classifier: Programming Language :: Python :: 3.9
Requires-Dist: django (>=3,<4)
